README.md
setup.py
csplookup/__init__.py
csplookup/csplookup.py
csplookup/errors.py
csplookup/result.py
csplookup.egg-info/PKG-INFO
csplookup.egg-info/SOURCES.txt
csplookup.egg-info/dependency_links.txt
csplookup.egg-info/requires.txt
csplookup.egg-info/top_level.txt