Metadata-Version: 2.1
Name: csplookup
Version: 1.4
Summary: Client library for CSP Lookup API.
Home-page: https://github.com/Navid2zp/csplookup-py
Author: Navid Zarepak
Author-email: navid2zp@gmail.com
License: MIT
Download-URL: https://pypi.org/project/csplookup/
Platform: UNKNOWN
